[{"name":"@dpuse/dpuse-shared","installedVersion":"0.3.594","author":"Jonathan Terrell <terrell.jm@gmail.com>","licenseType":"MIT","link":"git+https://github.com/data-positioning/dpuse-shared.git","definedVersion":"^0.3.594","remoteVersion":"0.3.595","alias":"","department":"n/a","relatedTo":"n/a","licensePeriod":"n/a","material":"n/a","requires":[]},{"name":"acorn","installedVersion":"8.16.0","author":"n/a","licenseType":"MIT","link":"git+https://github.com/acornjs/acorn.git","definedVersion":"^8.16.0","remoteVersion":"8.16.0","alias":"","department":"n/a","relatedTo":"n/a","licensePeriod":"n/a","material":"n/a","requires":[]},{"name":"acorn-typescript","installedVersion":"1.4.13","author":"tyrealhu","licenseType":"MIT","link":"git+https://github.com/TyrealHu/acorn-typescript.git","definedVersion":"^1.4.13","remoteVersion":"1.4.13","alias":"","requires":[{"name":"acorn","installedVersion":"8.16.0","author":"n/a","licenseType":"MIT","link":"git+https://github.com/acornjs/acorn.git","definedVersion":"^8.16.0","remoteVersion":"8.16.0","alias":"","department":"n/a","relatedTo":"n/a","licensePeriod":"n/a","material":"n/a","requires":[]}],"department":"n/a","relatedTo":"n/a","licensePeriod":"n/a","material":"n/a"},{"name":"acorn-walk","installedVersion":"8.3.5","author":"n/a","licenseType":"MIT","link":"git+https://github.com/acornjs/acorn.git","definedVersion":"^8.3.5","remoteVersion":"8.3.5","alias":"","requires":[{"name":"acorn","installedVersion":"8.16.0","author":"n/a","licenseType":"MIT","link":"git+https://github.com/acornjs/acorn.git","definedVersion":"^8.16.0","remoteVersion":"8.16.0","alias":"","department":"n/a","relatedTo":"n/a","licensePeriod":"n/a","material":"n/a","requires":[]}],"department":"n/a","relatedTo":"n/a","licensePeriod":"n/a","material":"n/a"},{"name":"nanoid","installedVersion":"5.1.7","author":"Andrey Sitnik <andrey@sitnik.ru>","licenseType":"MIT","link":"git+https://github.com/ai/nanoid.git","definedVersion":"^5.1.7","remoteVersion":"5.1.7","alias":"","department":"n/a","relatedTo":"n/a","licensePeriod":"n/a","material":"n/a","requires":[]},{"name":"valibot","installedVersion":"1.3.1","author":"Fabian Hiller","licenseType":"MIT","link":"git+https://github.com/open-circle/valibot.git","definedVersion":"^1.3.1","remoteVersion":"1.3.1","alias":"","requires":[{"name":"typescript","installedVersion":"5.9.3","author":"Microsoft Corp.","licenseType":"Apache-2.0","link":"git+https://github.com/microsoft/TypeScript.git","definedVersion":">=5","remoteVersion":"6.0.2","alias":"","department":"n/a","relatedTo":"n/a","licensePeriod":"n/a","material":"n/a","requires":[]}],"department":"n/a","relatedTo":"n/a","licensePeriod":"n/a","material":"n/a"}]